investimentos/__init__.py
investimentos/investimentos.py
AV_investimentos-0.5.dist-info/LICENSE
AV_investimentos-0.5.dist-info/METADATA
AV_investimentos-0.5.dist-info/WHEEL
AV_investimentos-0.5.dist-info/top_level.txt
AV_investimentos-0.5.dist-info/RECORD
